idletypecheck/__init__.py
idletypecheck/extension.py
idletypecheck/py.typed
idletypecheck/utils.py
idletypecheck-1.0.1.dist-info/LICENSE
idletypecheck-1.0.1.dist-info/METADATA
idletypecheck-1.0.1.dist-info/WHEEL
idletypecheck-1.0.1.dist-info/entry_points.txt
idletypecheck-1.0.1.dist-info/top_level.txt
idletypecheck-1.0.1.dist-info/RECORD
