Metadata-Version: 2.1
Name: idletypecheck
Version: 1.0.1
Summary: Mypy type checking extension for Python IDLE
Author-email: CoolCat467 <CoolCat467@duck.com>
License: GNU GENERAL PUBLIC LICENSE
Project-URL: Source, https://github.com/CoolCat467/idletypecheck
Project-URL: Bug Tracker, https://github.com/CoolCat467/idletypecheck/issues
Keywords: mypy,idle,extension,development
Classifier: Development Status :: 4 - Beta
Classifier: Intended Audience :: Developers
Classifier: License :: OSI Approved :: GNU General Public License v3 (GPLv3)
Classifier: Natural Language :: English
Classifier: Programming Language :: Python :: 3
Classifier: Programming Language :: Python :: 3.10
Classifier: Programming Language :: Python :: 3.11
Classifier: Programming Language :: Python :: 3.12
Classifier: Programming Language :: Python :: 3 :: Only
Classifier: Topic :: Software Development
Classifier: Topic :: Text Editors :: Integrated Development Environments (IDE)
Classifier: Topic :: Utilities
Classifier: Operating System :: OS Independent
Classifier: Framework :: IDLE
Classifier: Topic :: Utilities
Classifier: Typing :: Typed
Requires-Python: >=3.10
License-File: LICENSE
Requires-Dist: mypy >=1.8.0
Provides-Extra: user
Requires-Dist: idleuserextend ~=0.0.1 ; extra == 'user'
